{
  "flow_type": "data_list",
  "flow_name": "w_crisis_specific_task_gs",
  "status": "released",
  "rows": [
    {
      "id": "read_1",
      "individual": true,
      "together": true,
      "priority": 11,
      "title": "Story 1"
    },
    {
      "id": "read_2",
      "individual": true,
      "together": true,
      "priority": 13,
      "title": "Story 2"
    },
    {
      "id": "learn",
      "individual": true,
      "together": true,
      "priority": 71,
      "title": "Learn"
    }
  ],
  "_xlsxPath": "global/data/workshop_data/workshop_task_groups.xlsx"
}