{
  "flow_type": "template",
  "flow_name": "efm_act_2_110a_template",
  "status": "released",
  "rows": [
    {
      "type": "template",
      "name": "activity_body",
      "value": "efm_activity_body_template",
      "rows": [
        {
          "name": "text_top_1",
          "value": "Create a stack of Number Cards with a range of quantities your child is comfortable with. Split the cards evenly between two players and place the cards face down. The players take turns placing a single card on the stack in the middle between them. If the card is one more, same, or one less than the previous card, the first player to yell out the relationship claims the whole pile.",
          "_translations": {
            "value": {}
          },
          "type": "set_variable",
          "_nested_name": "activity_body.text_top_1"
        },
        {
          "name": "image_middle_1",
          "value": "EFM110WithinOneorTwo.svg",
          "_translations": {
            "value": {}
          },
          "type": "set_variable",
          "_nested_name": "activity_body.image_middle_1"
        },
        {
          "name": "image_middle_1_max_width",
          "value": "360px",
          "_translations": {
            "value": {}
          },
          "type": "set_variable",
          "_nested_name": "activity_body.image_middle_1_max_width"
        },
        {
          "name": "text_bottom_1",
          "value": "This can be extended to include the relationships of two more or two less as options. Another variation is to use a target sum, say 10 – yell out whenever the top two cards add up to the target.",
          "_translations": {
            "value": {}
          },
          "type": "set_variable",
          "_nested_name": "activity_body.text_bottom_1"
        }
      ],
      "_nested_name": "activity_body"
    }
  ],
  "_xlsxPath": "EFM_activity_chapter2_sheets.xlsx"
}