{
  "flow_type": "template",
  "module": "crisis",
  "flow_name": "w_crisis_m_w_tomorrow",
  "status": "released",
  "rows": [
    {
      "name": "workshop_data",
      "value": "@data.workshop.w_crisis",
      "_translations": {
        "value": {}
      }
    },
    {
      "type": "template",
      "name": "m_workshop_tomorrow",
      "value": "m_workshop_tomorrow",
      "rows": [
        {
          "name": "workshop_data",
          "value": "@local.workshop_data",
          "_translations": {
            "value": {}
          }
        },
        {
          "name": "text_not_completed",
          "value": "Tomorrow the final @global.parent_app workshop is ready for you. \n\nTry to complete @local.workshop_data.in_text_title before starting the new workshop. That way, you can complete your set of parenting skills and decide what to do next!",
          "_translations": {
            "value": {
              "tz_sw": true,
              "za_af": true,
              "za_st": true,
              "za_tn": true,
              "za_xh": true,
              "za_zu": true
            }
          }
        },
        {
          "name": "text_completed",
          "value": "Well done for completing @local.workshop_data.in_text_title. Tomorrow, you can access the final workshop to reflect on your @global.parent_app journey and on what you can do next!",
          "_translations": {
            "value": {
              "tz_sw": true,
              "za_af": true,
              "za_st": true,
              "za_tn": true,
              "za_xh": true,
              "za_zu": true
            }
          }
        }
      ]
    }
  ],
  "_xlsxPath": "global/in_week_messages/in_week_message_texts/w_crisis_messages.xlsx"
}