{
  "flow_type": "template",
  "module": "money",
  "flow_name": "w_money_tq_3",
  "status": "released",
  "rows": [
    {
      "type": "template",
      "name": "talk_group_family",
      "value": "talk_together",
      "action_list": [
        {
          "trigger": "completed",
          "action_id": "emit",
          "args": [
            "completed"
          ],
          "_raw": "completed | emit:completed",
          "_cleaned": "completed | emit:completed"
        },
        {
          "trigger": "uncompleted",
          "action_id": "emit",
          "args": [
            "uncompleted"
          ],
          "_raw": "uncompleted | emit:uncompleted",
          "_cleaned": "uncompleted | emit:uncompleted"
        }
      ],
      "condition": "@fields.do_this_workshop_together || @fields.w_money_path==\"family\"",
      "rows": [
        {
          "type": "nested_properties",
          "name": "workshop_activity",
          "rows": [
            {
              "name": "intro_text",
              "value": "Let's talk about different ways we can save.",
              "_translations": {
                "value": {
                  "tz_sw": true
                }
              },
              "type": "set_variable",
              "_nested_name": "talk_group_family.workshop_activity.intro_text"
            },
            {
              "type": "nested_properties",
              "name": "content_box",
              "rows": [
                {
                  "name": "text",
                  "value": "Discuss together: \n* In which different ways can we save?  \n* What are the advantages and disadvantages of each savings option? \n\nUnderstanding each option well will help you to decide what is the best saving option for your family.  \n\nWhatever savings plan you choose, it will really help your family move forward!",
                  "_translations": {
                    "value": {
                      "tz_sw": true
                    }
                  },
                  "type": "set_variable",
                  "_nested_name": "talk_group_family.workshop_activity.content_box.text"
                },
                {
                  "name": "button_1",
                  "action_list": [
                    {
                      "trigger": "click",
                      "action_id": "pop_up",
                      "args": [
                        "w_money_tq_3_pop"
                      ],
                      "_raw": "click | pop_up:w_money_tq_3_pop",
                      "_cleaned": "click | pop_up:w_money_tq_3_pop"
                    }
                  ],
                  "hidden": false,
                  "type": "set_variable",
                  "_nested_name": "talk_group_family.workshop_activity.content_box.button_1"
                }
              ],
              "_nested_name": "talk_group_family.workshop_activity.content_box"
            }
          ],
          "_nested_name": "talk_group_family.workshop_activity"
        }
      ],
      "_nested_name": "talk_group_family",
      "_dynamicFields": {
        "condition": [
          {
            "fullExpression": "@fields.do_this_workshop_together || @fields.w_money_path==\"family\"",
            "matchedExpression": "@fields.do_this_workshop_together",
            "type": "fields",
            "fieldName": "do_this_workshop_together"
          },
          {
            "fullExpression": "@fields.do_this_workshop_together || @fields.w_money_path==\"family\"",
            "matchedExpression": "@fields.w_money_path",
            "type": "fields",
            "fieldName": "w_money_path"
          }
        ]
      },
      "_dynamicDependencies": {
        "@fields.do_this_workshop_together": [
          "condition"
        ],
        "@fields.w_money_path": [
          "condition"
        ]
      }
    },
    {
      "type": "template",
      "name": "question_alone",
      "value": "question_time",
      "action_list": [
        {
          "trigger": "completed",
          "action_id": "emit",
          "args": [
            "completed"
          ],
          "_raw": "completed | emit:completed",
          "_cleaned": "completed | emit:completed"
        },
        {
          "trigger": "uncompleted",
          "action_id": "emit",
          "args": [
            "uncompleted"
          ],
          "_raw": "uncompleted | emit:uncompleted",
          "_cleaned": "uncompleted | emit:uncompleted"
        }
      ],
      "condition": "!(@fields.do_this_workshop_together || @fields.w_money_path==\"family\")",
      "rows": [
        {
          "type": "nested_properties",
          "name": "workshop_activity",
          "rows": [
            {
              "name": "intro_text",
              "value": "Let's think about different ways we can save.",
              "_translations": {
                "value": {
                  "tz_sw": true
                }
              },
              "type": "set_variable",
              "_nested_name": "question_alone.workshop_activity.intro_text"
            },
            {
              "type": "nested_properties",
              "name": "content_box",
              "value": "box_combo_box",
              "rows": [
                {
                  "name": "combo_box_tracker",
                  "value": "w_money_tq_3_a",
                  "_translations": {
                    "value": {}
                  },
                  "exclude_from_translation": true,
                  "type": "set_variable",
                  "_nested_name": "question_alone.workshop_activity.content_box.combo_box_tracker"
                },
                {
                  "name": "text",
                  "value": "There are different ways we can save: at home, buying things we can sell later, at a bank, or in a savings group.\n\nThink of the advantages and disadvantages of each savings option.",
                  "_translations": {
                    "value": {
                      "tz_sw": true
                    }
                  },
                  "type": "set_variable",
                  "_nested_name": "question_alone.workshop_activity.content_box.text"
                },
                {
                  "name": "question_text",
                  "value": "What is the best savings option for your family?",
                  "_translations": {
                    "value": {
                      "tz_sw": true
                    }
                  },
                  "type": "set_variable",
                  "_nested_name": "question_alone.workshop_activity.content_box.question_text"
                },
                {
                  "name": "answer_list",
                  "value": [
                    "name:name_1 | text:@global.savings_option_1",
                    "name:name_2 | text:@global.savings_option_2",
                    "name:name_3 | text:@global.savings_option_3",
                    "name:name_4 | text:@global.savings_option_4"
                  ],
                  "type": "set_variable",
                  "_nested_name": "question_alone.workshop_activity.content_box.answer_list",
                  "_dynamicFields": {
                    "value": {
                      "0": [
                        {
                          "fullExpression": "name:name_1 | text:@global.savings_option_1",
                          "matchedExpression": "@global.savings_option_1",
                          "type": "global",
                          "fieldName": "savings_option_1"
                        }
                      ],
                      "1": [
                        {
                          "fullExpression": "name:name_2 | text:@global.savings_option_2",
                          "matchedExpression": "@global.savings_option_2",
                          "type": "global",
                          "fieldName": "savings_option_2"
                        }
                      ],
                      "2": [
                        {
                          "fullExpression": "name:name_3 | text:@global.savings_option_3",
                          "matchedExpression": "@global.savings_option_3",
                          "type": "global",
                          "fieldName": "savings_option_3"
                        }
                      ],
                      "3": [
                        {
                          "fullExpression": "name:name_4 | text:@global.savings_option_4",
                          "matchedExpression": "@global.savings_option_4",
                          "type": "global",
                          "fieldName": "savings_option_4"
                        }
                      ]
                    }
                  },
                  "_dynamicDependencies": {
                    "@global.savings_option_1": [
                      "value.0"
                    ],
                    "@global.savings_option_2": [
                      "value.1"
                    ],
                    "@global.savings_option_3": [
                      "value.2"
                    ],
                    "@global.savings_option_4": [
                      "value.3"
                    ]
                  }
                },
                {
                  "name": "reply",
                  "value": "Whatever savings plan you choose, it will really help your family move forward!",
                  "_translations": {
                    "value": {
                      "tz_sw": true
                    }
                  },
                  "type": "set_variable",
                  "_nested_name": "question_alone.workshop_activity.content_box.reply"
                }
              ],
              "_nested_name": "question_alone.workshop_activity.content_box"
            }
          ],
          "_nested_name": "question_alone.workshop_activity"
        }
      ],
      "_nested_name": "question_alone",
      "_dynamicFields": {
        "condition": [
          {
            "fullExpression": "!(@fields.do_this_workshop_together || @fields.w_money_path==\"family\")",
            "matchedExpression": "@fields.do_this_workshop_together",
            "type": "fields",
            "fieldName": "do_this_workshop_together"
          },
          {
            "fullExpression": "!(@fields.do_this_workshop_together || @fields.w_money_path==\"family\")",
            "matchedExpression": "@fields.w_money_path",
            "type": "fields",
            "fieldName": "w_money_path"
          }
        ]
      },
      "_dynamicDependencies": {
        "@fields.do_this_workshop_together": [
          "condition"
        ],
        "@fields.w_money_path": [
          "condition"
        ]
      }
    }
  ],
  "_xlsxPath": "global/top_templates/workshop_templates/workshop_money.xlsx"
}