{
  "flow_type": "template",
  "module": "rules",
  "flow_name": "w_rules_stepper",
  "status": "released",
  "rows": [
    {
      "type": "template",
      "name": "workshop_stepper_actions",
      "value": "workshop_stepper_actions",
      "action_list": [
        {
          "trigger": "completed",
          "action_id": "emit",
          "args": [
            "completed"
          ],
          "_raw": "completed | emit:completed",
          "_cleaned": "completed | emit:completed"
        },
        {
          "trigger": "uncompleted",
          "action_id": "emit",
          "args": [
            "uncompleted"
          ],
          "_raw": "uncompleted | emit:uncompleted",
          "_cleaned": "uncompleted | emit:uncompleted"
        }
      ],
      "rows": [
        {
          "name": "workshop_id",
          "value": "w_rules",
          "_translations": {
            "value": {}
          },
          "exclude_from_translation": true,
          "type": "set_variable",
          "_nested_name": "workshop_stepper_actions.workshop_id"
        },
        {
          "type": "nested_properties",
          "name": "workshop_stepper",
          "rows": [
            {
              "name": "nav_template_list",
              "value": [
                "w_rules_care_together",
                "w_rules_relax",
                "w_rules_reflect_together",
                "w_rules_intro",
                "w_rules_read_1",
                "w_rules_talk",
                "w_rules_tools_activity",
                "w_rules_read_2",
                "w_rules_try",
                "w_rules_home_practice",
                "w_rules_ending"
              ],
              "condition": "@field.do_this_workshop_together",
              "exclude_from_translation": true,
              "type": "set_variable",
              "_nested_name": "workshop_stepper_actions.workshop_stepper.nav_template_list",
              "_dynamicFields": {
                "condition": [
                  {
                    "fullExpression": "@field.do_this_workshop_together",
                    "matchedExpression": "@field.do_this_workshop_together",
                    "type": "field",
                    "fieldName": "do_this_workshop_together"
                  }
                ]
              },
              "_dynamicDependencies": {
                "@field.do_this_workshop_together": [
                  "condition"
                ]
              }
            },
            {
              "name": "nav_template_list",
              "value": [
                "w_rules_welcome_individual",
                "w_rules_relax",
                "w_rules_intro",
                "w_rules_read_1",
                "w_rules_question",
                "w_rules_tools_activity",
                "w_rules_read_2",
                "w_rules_learn_temp",
                "w_rules_home_practice",
                "w_rules_ending"
              ],
              "condition": "!@field.do_this_workshop_together",
              "exclude_from_translation": true,
              "type": "set_variable",
              "_nested_name": "workshop_stepper_actions.workshop_stepper.nav_template_list",
              "_dynamicFields": {
                "condition": [
                  {
                    "fullExpression": "!@field.do_this_workshop_together",
                    "matchedExpression": "!@field.do_this_workshop_together",
                    "type": "field",
                    "fieldName": "do_this_workshop_together"
                  }
                ]
              },
              "_dynamicDependencies": {
                "!@field.do_this_workshop_together": [
                  "condition"
                ]
              }
            }
          ],
          "_nested_name": "workshop_stepper_actions.workshop_stepper"
        }
      ],
      "_nested_name": "workshop_stepper_actions"
    }
  ],
  "_xlsxPath": "global/top_templates/workshop_templates/workshop_rules.xlsx"
}