{
  "flow_type": "tour",
  "flow_name": "ae_topics_tour",
  "status": "released",
  "rows": [
    {
      "type": "step",
      "title": "Pests",
      "_translations": {
        "title": {},
        "message_text": {}
      },
      "message_text": "Did you know that we have beneficial pests? Learn more about managing pests through agricultural practices such as plant diversity, and efficient use of non-toxic pesticides.",
      "template_component_name": "tile_pests",
      "route": "template/topics_screen"
    },
    {
      "type": "step",
      "title": "Nutrition",
      "_translations": {
        "title": {},
        "message_text": {}
      },
      "message_text": "Nutrition is a critical part of health and development. Explore this category to learn more about the different food types and nutrients that are necessary for you and your family.",
      "template_component_name": "tile_nutrition",
      "route": "template/topics_screen"
    },
    {
      "type": "step",
      "title": "Soil Health",
      "_translations": {
        "title": {},
        "message_text": {}
      },
      "message_text": "Healthy soil is the foundation of productive and sustainable food production. Learn here about the principles of soil health and usable best practices.",
      "template_component_name": "tile_soils",
      "route": "template/topics_screen"
    }
  ],
  "_xlsxPath": "tours/global/navigation_tours.xlsx"
}